albi0/__init__.py
albi0/__main__.py
albi0/api.py
albi0/bytes_reader.py
albi0/cli/__init__.py
albi0/cli/commands/__init__.py
albi0/cli/commands/extract.py
albi0/cli/commands/list.py
albi0/cli/commands/update.py
albi0/container.py
albi0/extract/__init__.py
albi0/extract/extractor.py
albi0/extract/registry.py
albi0/log.py
albi0/plugins/__init__.py
albi0/plugins/newseer.py
albi0/plugins/seerproject.py
albi0/request.py
albi0/typing.py
albi0/update/__init__.py
albi0/update/downloader.py
albi0/update/updater.py
albi0/update/version.py
albi0/updaters/__init__.py
albi0/updaters/yoo_version_manager.py
albi0/utils.py
albi0-0.5.1.dist-info/WHEEL
albi0-0.5.1.dist-info/entry_points.txt
albi0-0.5.1.dist-info/METADATA
albi0-0.5.1.dist-info/RECORD
