Metadata-Version: 2.4
Name: albi0
Version: 0.5.1
Summary: Plugin-based Unity Asset Extractor
Keywords: unity,asset,extractor,plugin,game,seer
Author: Nattsu39
Author-email: Nattsu39 <nattsu39@outlook.com>
License-Expression: MIT
Classifier: Operating System :: OS Independent
Classifier: Programming Language :: Python :: 3
Requires-Dist: asyncer>=0.0.8
Requires-Dist: anyio>=4.6.2.post1
Requires-Dist: tqdm>=4.67.0
Requires-Dist: httpx>=0.27.2
Requires-Dist: click>=8.1.7
Requires-Dist: orjson>=3.10.11
Requires-Dist: unitypy>=1.23
Requires-Dist: loguru>=0.7.2
Requires-Dist: aiofiles>=24.1.0
Requires-Dist: slpp>=1.2.3
Requires-Dist: dataclasses-json>=0.6.7
Requires-Python: >=3.10
Project-URL: Bug Tracker, https://github.com/SeerAPI/albi0/issues
Project-URL: Homepage, https://github.com/SeerAPI/albi0
Project-URL: Repository, https://github.com/SeerAPI/albi0
